[{"line":"91","stop_id":2344,"service_canceled":false,"service_changed":false,"service_replaced":true,"stop_canceled":false,"stop_relocated":false,"route_changed":false,"owl_service_canceled":false},{"line":"91","stop_id":2346,"service_canceled":false,"service_changed":false,"service_replaced":true,"stop_canceled":false,"stop_relocated":false,"route_changed":false,"owl_service_canceled":false},{"line":"91","stop_id":2521,"service_canceled":false,"service_changed":false,"service_replaced":true,"stop_canceled":false,"stop_relocated":false,"route_changed":false,"owl_service_canceled":false},{"line":"91","stop_id":2520,"service_canceled":false,"service_changed":false,"service_replaced":true,"stop_canceled":false,"stop_relocated":false,"route_changed":false,"owl_service_canceled":false},{"line":"91","stop_id":2771,"service_canceled":false,"service_changed":false,"service_replaced":true,"stop_canceled":false,"stop_relocated":false,"route_changed":false,"owl_service_canceled":false},{"line":"91","stop_id":2770,"service_canceled":false,"service_changed":false,"service_replaced":true,"stop_canceled":false,"stop_relocated":false,"route_changed":false,"owl_service_canceled":false},{"line":"91","stop_id":2769,"service_canceled":false,"service_changed":false,"service_replaced":true,"stop_canceled":false,"stop_relocated":false,"route_changed":false,"owl_service_canceled":false},{"line":"91","stop_id":11263,"service_canceled":false,"service_changed":false,"service_replaced":true,"stop_canceled":false,"stop_relocated":false,"route_changed":false,"owl_service_canceled":false},{"line":"91","stop_id":17784,"service_canceled":false,"service_changed":false,"service_replaced":true,"stop_canceled":false,"stop_relocated":false,"route_changed":false,"owl_service_canceled":false},{"line":"91","stop_id":2020,"service_canceled":false,"service_changed":false,"service_replaced":true,"stop_canceled":false,"stop_relocated":false,"route_changed":false,"owl_service_canceled":false},{"line":"91","stop_id":10600,"service_canceled":false,"service_changed":false,"service_replaced":true,"stop_canceled":false,"stop_relocated":false,"route_changed":false,"owl_service_canceled":false},{"line":"91","stop_id":2045,"service_canceled":false,"service_changed":false,"service_replaced":true,"stop_canceled":false,"stop_relocated":false,"route_changed":false,"owl_service_canceled":false},{"line":"91","stop_id":10595,"service_canceled":false,"service_changed":false,"service_replaced":true,"stop_canceled":false,"stop_relocated":false,"route_changed":false,"owl_service_canceled":false},{"line":"91","stop_id":2050,"service_canceled":false,"service_changed":false,"service_replaced":true,"stop_canceled":false,"stop_relocated":false,"route_changed":false,"owl_service_canceled":false},{"line":"91","stop_id":10571,"service_canceled":false,"service_changed":false,"service_replaced":true,"stop_canceled":false,"stop_relocated":false,"route_changed":false,"owl_service_canceled":false},{"line":"91","stop_id":10551,"service_canceled":false,"service_changed":false,"service_replaced":true,"stop_canceled":false,"stop_relocated":false,"route_changed":false,"owl_service_canceled":false},{"line":"91","stop_id":2772,"service_canceled":false,"service_changed":false,"service_replaced":true,"stop_canceled":false,"stop_relocated":false,"route_changed":false,"owl_service_canceled":false},{"line":"91","stop_id":11264,"service_canceled":false,"service_changed":false,"service_replaced":true,"stop_canceled":false,"stop_relocated":false,"route_changed":false,"owl_service_canceled":false},{"line":"91","stop_id":11265,"service_canceled":false,"service_changed":false,"service_replaced":true,"stop_canceled":false,"stop_relocated":false,"route_changed":false,"owl_service_canceled":false},{"line":"91","stop_id":11266,"service_canceled":false,"service_changed":false,"service_replaced":true,"stop_canceled":false,"stop_relocated":false,"route_changed":false,"owl_service_canceled":false},{"line":"91","stop_id":11054,"service_canceled":false,"service_changed":false,"service_replaced":true,"stop_canceled":false,"stop_relocated":false,"route_changed":false,"owl_service_canceled":false},{"line":"91","stop_id":11057,"service_canceled":false,"service_changed":false,"service_replaced":true,"stop_canceled":false,"stop_relocated":false,"route_changed":false,"owl_service_canceled":false},{"line":"91","stop_id":11055,"service_canceled":false,"service_changed":false,"service_replaced":true,"stop_canceled":false,"stop_relocated":false,"route_changed":false,"owl_service_canceled":false},{"line":"91","stop_id":11056,"service_canceled":false,"service_changed":false,"service_replaced":true,"stop_canceled":false,"stop_relocated":false,"route_changed":false,"owl_service_canceled":false},{"line":"91","stop_id":17783,"service_canceled":false,"service_changed":false,"service_replaced":true,"stop_canceled":false,"stop_relocated":false,"route_changed":false,"owl_service_canceled":false}]