[{"stop_id":"9673","stop_name":"120th \/ San Pedro"},{"stop_id":"4800004","stop_name":"23rd \/ Main"},{"stop_id":"4800005","stop_name":"23rd \/ Maple"},{"stop_id":"15778","stop_name":"8th \/ Broadway"},{"stop_id":"15788","stop_name":"8th \/ Hill"},{"stop_id":"7439","stop_name":"9th \/ Broadway"},{"stop_id":"3203","stop_name":"Arden Layover"},{"stop_id":"8828","stop_name":"Avalon \/ 120th"},{"stop_id":"8818","stop_name":"Avalon Station"},{"stop_id":"730","stop_name":"Clinton \/ Hoover"},{"stop_id":"24251|24252","stop_name":"Clinton \/ Virgil"},{"stop_id":"9984","stop_name":"Gage \/ Main"},{"stop_id":"1453","stop_name":"Gage \/ San Pedro"},{"stop_id":"5133|12102","stop_name":"Hill \/ 1st"},{"stop_id":"5135|4771","stop_name":"Hill \/ 3rd"},{"stop_id":"13596|12409","stop_name":"Hill \/ 4th"},{"stop_id":"13597|40","stop_name":"Hill \/ 5th"},{"stop_id":"13598","stop_name":"Hill \/ 6th"},{"stop_id":"2456|13600","stop_name":"Hill \/ 7th"},{"stop_id":"5142","stop_name":"Hill \/ 8th"},{"stop_id":"16381","stop_name":"Hill \/ Temple"},{"stop_id":"3632|12117","stop_name":"Hoover \/ Bellevue"},{"stop_id":"12118","stop_name":"Hoover \/ Clinton"},{"stop_id":"2523|11061","stop_name":"Hoover \/ Plata"},{"stop_id":"13700|1131","stop_name":"Main \/ 11th"},{"stop_id":"3121","stop_name":"Main \/ 16th"},{"stop_id":"5260","stop_name":"Main \/ 41st"},{"stop_id":"5261","stop_name":"Main \/ 43rd"},{"stop_id":"5262","stop_name":"Main \/ 46th"},{"stop_id":"5263","stop_name":"Main \/ 47th"},{"stop_id":"5264","stop_name":"Main \/ 49th"},{"stop_id":"5266","stop_name":"Main \/ 51st"},{"stop_id":"5267","stop_name":"Main \/ 53rd"},{"stop_id":"5268","stop_name":"Main \/ 54th"},{"stop_id":"5269","stop_name":"Main \/ 55th"},{"stop_id":"5270","stop_name":"Main \/ 59th"},{"stop_id":"5272","stop_name":"Main \/ 61st"},{"stop_id":"13714|5292","stop_name":"Main \/ 9th"},{"stop_id":"3115","stop_name":"Main \/ Martin Luther King Jr"},{"stop_id":"5279|13716","stop_name":"Main \/ Pico"},{"stop_id":"5297","stop_name":"Main \/ Slauson"},{"stop_id":"11606","stop_name":"Main \/ Venice"},{"stop_id":"5280","stop_name":"Main \/ Vernon"},{"stop_id":"4800003","stop_name":"Main \/ Washington"},{"stop_id":"5503","stop_name":"Manchester \/ San Pedro"},{"stop_id":"7830","stop_name":"Manchester Layover"},{"stop_id":"3149","stop_name":"Maple \/ 30th"},{"stop_id":"3150","stop_name":"Maple \/ 36th"},{"stop_id":"3151","stop_name":"Maple \/ 38th"},{"stop_id":"3154","stop_name":"Maple \/ Adams"},{"stop_id":"3155","stop_name":"Maple \/ Jefferson"},{"stop_id":"11689|11688","stop_name":"Melrose \/ Alexandria"},{"stop_id":"3202","stop_name":"Melrose \/ Arden"},{"stop_id":"3209|11697","stop_name":"Melrose \/ Crescent Heights"},{"stop_id":"11698","stop_name":"Melrose \/ Edgemont"},{"stop_id":"17013|11699","stop_name":"Melrose \/ Fairfax"},{"stop_id":"3210|11700","stop_name":"Melrose \/ Gardner"},{"stop_id":"3211|11701","stop_name":"Melrose \/ Harper"},{"stop_id":"3212|11702","stop_name":"Melrose \/ Harvard"},{"stop_id":"3205","stop_name":"Melrose \/ Heliotrope"},{"stop_id":"3213|11703","stop_name":"Melrose \/ Highland"},{"stop_id":"3206|11694","stop_name":"Melrose \/ Huntley"},{"stop_id":"3214|11704","stop_name":"Melrose \/ June"},{"stop_id":"3215|11705","stop_name":"Melrose \/ La Brea"},{"stop_id":"3216|11706","stop_name":"Melrose \/ La Cienega"},{"stop_id":"3217|11707","stop_name":"Melrose \/ Larchmont"},{"stop_id":"3219|11709","stop_name":"Melrose \/ Madison"},{"stop_id":"3220|11710","stop_name":"Melrose \/ Martel"},{"stop_id":"3221|11711","stop_name":"Melrose \/ Normandie"},{"stop_id":"3222|11712","stop_name":"Melrose \/ Ogden"},{"stop_id":"3224|11714","stop_name":"Melrose \/ Orlando"},{"stop_id":"3225|11715","stop_name":"Melrose \/ Poinsettia"},{"stop_id":"3226|4963","stop_name":"Melrose \/ Spaulding"},{"stop_id":"3227|11718","stop_name":"Melrose \/ Van Ness"},{"stop_id":"3228|11719","stop_name":"Melrose \/ Vermont"},{"stop_id":"11691","stop_name":"Melrose \/ Vine"},{"stop_id":"3229|24250","stop_name":"Melrose \/ Virgil"},{"stop_id":"3230|11721","stop_name":"Melrose \/ Western"},{"stop_id":"3233|11724","stop_name":"Melrose \/ Wilcox"},{"stop_id":"3231|11722","stop_name":"Melrose \/ Wilton"},{"stop_id":"3232|11723","stop_name":"Melrose \/ Windsor"},{"stop_id":"5473","stop_name":"San Pedro \/ 104th"},{"stop_id":"5474","stop_name":"San Pedro \/ 108th"},{"stop_id":"5475","stop_name":"San Pedro \/ 109th"},{"stop_id":"5476","stop_name":"San Pedro \/ 111th"},{"stop_id":"5477","stop_name":"San Pedro \/ 116th"},{"stop_id":"5478","stop_name":"San Pedro \/ 118th"},{"stop_id":"5487","stop_name":"San Pedro \/ 67th"},{"stop_id":"5489","stop_name":"San Pedro \/ 76th"},{"stop_id":"25260","stop_name":"San Pedro \/ 77th"},{"stop_id":"5881","stop_name":"San Pedro \/ 79th"},{"stop_id":"13882","stop_name":"San Pedro \/ 82nd"},{"stop_id":"5492","stop_name":"San Pedro \/ 83rd"},{"stop_id":"5493","stop_name":"San Pedro \/ 88th"},{"stop_id":"5495","stop_name":"San Pedro \/ 92nd"},{"stop_id":"5498","stop_name":"San Pedro \/ Century"},{"stop_id":"5499","stop_name":"San Pedro \/ Colden"},{"stop_id":"5500","stop_name":"San Pedro \/ Florence"},{"stop_id":"4713","stop_name":"San Pedro \/ Imperial"},{"stop_id":"1556","stop_name":"San Pedro \/ Manchester"},{"stop_id":"2192|11716","stop_name":"San Vicente \/ Melrose"},{"stop_id":"6000","stop_name":"Santa Monica \/ Larrabee"},{"stop_id":"4719|12425","stop_name":"Temple \/ Alvarado"},{"stop_id":"8088","stop_name":"Temple \/ Beaudry"},{"stop_id":"16369","stop_name":"Temple \/ Belmont"},{"stop_id":"8089|4723","stop_name":"Temple \/ Bonnie Brae"},{"stop_id":"8090|16376","stop_name":"Temple \/ Boylston"},{"stop_id":"8092","stop_name":"Temple \/ Carondelet"},{"stop_id":"8085|16371","stop_name":"Temple \/ Douglas"},{"stop_id":"8086|8966","stop_name":"Temple \/ Edgeware"},{"stop_id":"8094|8093","stop_name":"Temple \/ Figueroa"},{"stop_id":"8087|16373","stop_name":"Temple \/ Glendale"},{"stop_id":"3587|8095","stop_name":"Temple \/ Grand"},{"stop_id":"24249|16382","stop_name":"Temple \/ Hoover"},{"stop_id":"8099|16383","stop_name":"Temple \/ Occidental"},{"stop_id":"4724","stop_name":"Temple \/ Park View"},{"stop_id":"8100|16384","stop_name":"Temple \/ Rampart"},{"stop_id":"8106|16388","stop_name":"Temple \/ Robinson"},{"stop_id":"3947|12426","stop_name":"Temple \/ Rosemont"},{"stop_id":"8102","stop_name":"Temple \/ Union"},{"stop_id":"8103|16386","stop_name":"Temple \/ Vendome"}]