[{"stop_id":"9667|1134","stop_name":"120th \/ Avalon"},{"stop_id":"1136|9671","stop_name":"120th \/ Central"},{"stop_id":"1142|9675","stop_name":"120th \/ Wadsworth"},{"stop_id":"4861","stop_name":"5th \/ Central"},{"stop_id":"15690","stop_name":"5th \/ Flower"},{"stop_id":"15688","stop_name":"5th \/ Grand"},{"stop_id":"15694","stop_name":"5th \/ Hill"},{"stop_id":"8634","stop_name":"5th \/ Los Angeles"},{"stop_id":"9737","stop_name":"5th \/ San Pedro"},{"stop_id":"7333","stop_name":"5th \/ Spring"},{"stop_id":"9738","stop_name":"5th \/ Towne"},{"stop_id":"1204","stop_name":"5th \/ Wall"},{"stop_id":"7345","stop_name":"6th \/ Broadway"},{"stop_id":"140995","stop_name":"6th \/ Grand"},{"stop_id":"5138","stop_name":"6th \/ Hill"},{"stop_id":"9744","stop_name":"6th \/ Los Angeles"},{"stop_id":"1215","stop_name":"6th \/ San Pedro"},{"stop_id":"5585","stop_name":"6th \/ Spring"},{"stop_id":"1216","stop_name":"6th \/ Towne"},{"stop_id":"1217","stop_name":"6th \/ Wall"},{"stop_id":"283|8871","stop_name":"Avalon \/ Imperial"},{"stop_id":"8818|292","stop_name":"Avalon Station"},{"stop_id":"1731","stop_name":"Avalon Station Layover"},{"stop_id":"13180","stop_name":"Beaudry \/ 4th"},{"stop_id":"3705|13301","stop_name":"Central \/ 103rd"},{"stop_id":"4842|140755","stop_name":"Central \/ 105th"},{"stop_id":"4843","stop_name":"Central \/ 107th"},{"stop_id":"140786|13303","stop_name":"Central \/ 108th"},{"stop_id":"140785|13304","stop_name":"Central \/ 112th"},{"stop_id":"4845|13305","stop_name":"Central \/ 114th"},{"stop_id":"4847|13306","stop_name":"Central \/ 123rd"},{"stop_id":"4848|13307","stop_name":"Central \/ 12th"},{"stop_id":"3441|11929","stop_name":"Central \/ 131st"},{"stop_id":"3437|11930","stop_name":"Central \/ 139th"},{"stop_id":"140782","stop_name":"Central \/ 148th"},{"stop_id":"4849|140753","stop_name":"Central \/ 14th"},{"stop_id":"4896|13341","stop_name":"Central \/ 156th"},{"stop_id":"4850|13309","stop_name":"Central \/ 16th"},{"stop_id":"4851|13310","stop_name":"Central \/ 22nd"},{"stop_id":"625|9191","stop_name":"Central \/ 24th"},{"stop_id":"4852|13311","stop_name":"Central \/ 28th"},{"stop_id":"4853","stop_name":"Central \/ 32nd"},{"stop_id":"13312","stop_name":"Central \/ 33rd"},{"stop_id":"9196","stop_name":"Central \/ 35th"},{"stop_id":"4854|13313","stop_name":"Central \/ 41st"},{"stop_id":"4855|13314","stop_name":"Central \/ 42nd"},{"stop_id":"4856|13315","stop_name":"Central \/ 43rd"},{"stop_id":"4858|13316","stop_name":"Central \/ 46th"},{"stop_id":"4857","stop_name":"Central \/ 48th"},{"stop_id":"13317","stop_name":"Central \/ 49th"},{"stop_id":"4859|13318","stop_name":"Central \/ 51st"},{"stop_id":"13319","stop_name":"Central \/ 54th"},{"stop_id":"140927","stop_name":"Central \/ 55th"},{"stop_id":"13320","stop_name":"Central \/ 57th"},{"stop_id":"4862|13321","stop_name":"Central \/ 60th"},{"stop_id":"4863|13322","stop_name":"Central \/ 68th"},{"stop_id":"1213|3716","stop_name":"Central \/ 6th"},{"stop_id":"4865|13324","stop_name":"Central \/ 75th"},{"stop_id":"13325","stop_name":"Central \/ 76th"},{"stop_id":"4866","stop_name":"Central \/ 76th Pl"},{"stop_id":"9192","stop_name":"Central \/ 79th"},{"stop_id":"4867|13326","stop_name":"Central \/ 7th"},{"stop_id":"4868|13327","stop_name":"Central \/ 81st"},{"stop_id":"4869|13328","stop_name":"Central \/ 83rd"},{"stop_id":"13330","stop_name":"Central \/ 87th"},{"stop_id":"4872","stop_name":"Central \/ 87th Pl"},{"stop_id":"4873","stop_name":"Central \/ 88th"},{"stop_id":"13333","stop_name":"Central \/ 88th Pl"},{"stop_id":"4874|140752","stop_name":"Central \/ 8th"},{"stop_id":"4875|13335","stop_name":"Central \/ 90th"},{"stop_id":"629","stop_name":"Central \/ 91 Fwy Westbound Off-Ramp"},{"stop_id":"4876|13332","stop_name":"Central \/ 92nd"},{"stop_id":"13331","stop_name":"Central \/ 95th"},{"stop_id":"4877|4893","stop_name":"Central \/ 96th"},{"stop_id":"4878|13338","stop_name":"Central \/ Adams"},{"stop_id":"13334","stop_name":"Central \/ Albertoni"},{"stop_id":"4879|13339","stop_name":"Central \/ Alondra"},{"stop_id":"3442","stop_name":"Central \/ Brazil"},{"stop_id":"4897|13355","stop_name":"Central \/ Caldwell"},{"stop_id":"4880|140754","stop_name":"Central \/ Century"},{"stop_id":"3438|140783","stop_name":"Central \/ Compton"},{"stop_id":"4900|11932","stop_name":"Central \/ El Segundo"},{"stop_id":"4881|3700","stop_name":"Central \/ Florence"},{"stop_id":"4882|13343","stop_name":"Central \/ Gage"},{"stop_id":"4892|13352","stop_name":"Central \/ Greenleaf"},{"stop_id":"140787","stop_name":"Central \/ Hooper"},{"stop_id":"140784|1738","stop_name":"Central \/ Imperial"},{"stop_id":"627","stop_name":"Central \/ Jefferson"},{"stop_id":"4884|9197","stop_name":"Central \/ Lanzit"},{"stop_id":"633","stop_name":"Central \/ Mahalo"},{"stop_id":"4871|13345","stop_name":"Central \/ Manchester"},{"stop_id":"4895","stop_name":"Central \/ Nadeau"},{"stop_id":"4886|13346","stop_name":"Central \/ Olympic"},{"stop_id":"3444|11935","stop_name":"Central \/ Piru"},{"stop_id":"9194","stop_name":"Central \/ Radbard"},{"stop_id":"3440|11934","stop_name":"Central \/ Rosecrans"},{"stop_id":"4887|13348","stop_name":"Central \/ Slauson"},{"stop_id":"4889|3696","stop_name":"Central \/ Vernon"},{"stop_id":"9200|631","stop_name":"Central \/ Victoria"},{"stop_id":"13362","stop_name":"Central \/ Walnut"},{"stop_id":"3691|13351","stop_name":"Central \/ Washington"},{"stop_id":"2397","stop_name":"Grand \/ 2nd"},{"stop_id":"13560","stop_name":"Grand \/ 3rd"},{"stop_id":"10052|10051","stop_name":"Imperial \/ Wadsworth"},{"stop_id":"2345","stop_name":"Terminal 25"},{"stop_id":"1703","stop_name":"Victoria \/ Tamcliff"}]